jupyter_omero_authenticator/__init__.py
jupyter_omero_authenticator/auth.py
jupyter_omero_authenticator-0.0.1.data/data/share/jupyterhub/templates/omero_authenticator/omerologin.html
jupyter_omero_authenticator-0.0.1.dist-info/LICENSE
jupyter_omero_authenticator-0.0.1.dist-info/METADATA
jupyter_omero_authenticator-0.0.1.dist-info/WHEEL
jupyter_omero_authenticator-0.0.1.dist-info/top_level.txt
jupyter_omero_authenticator-0.0.1.dist-info/RECORD
