Metadata-Version: 2.1
Name: jupyter-omero-authenticator
Version: 0.0.1
Summary: Jupyterhub OMERO authenticator
Home-page: https://github.com/manics/jupyter-omero-authenticator
Author: Simon Li
License: MIT
Platform: UNKNOWN
Classifier: Framework :: Jupyter
Classifier: License :: OSI Approved :: MIT License
Classifier: Operating System :: OS Independent
Classifier: Programming Language :: Python
Classifier: Programming Language :: Python :: 3
Classifier: Topic :: Scientific/Engineering
Requires-Python: >=3.5
Requires-Dist: jupyterhub
Requires-Dist: omero-py (>=5.6.dev9)
